{
  "code": 200,
  "message": "message",
  "data": [
    {
      "apiMark": "data_0_apiMark",
      "apiMarkName": "data_0_apiMarkName",
      "apiDetailUrl": "http://test.com/data_0_apiDetailUrl",
      "apiUrl": "http://test.com/data_0_apiUrl",
      "apiPageUrl": "http://test.com/data_0_apiPageUrl",
      "id": 100
    },
    {
      "apiMark": "data_1_apiMark",
      "apiMarkName": "data_1_apiMarkName",
      "apiDetailUrl": "http://test.com/data_1_apiDetailUrl",
      "apiUrl": "http://test.com/data_1_apiUrl",
      "apiPageUrl": "http://test.com/data_1_apiPageUrl",
      "id": 101
    },
    {
      "apiMark": "data_2_apiMark",
      "apiMarkName": "data_2_apiMarkName",
      "apiDetailUrl": "http://test.com/data_2_apiDetailUrl",
      "apiUrl": "http://test.com/data_2_apiUrl",
      "apiPageUrl": "http://test.com/data_2_apiPageUrl",
      "id": 102
    },
    {
      "apiMark": "data_3_apiMark",
      "apiMarkName": "data_3_apiMarkName",
      "apiDetailUrl": "http://test.com/data_3_apiDetailUrl",
      "apiUrl": "http://test.com/data_3_apiUrl",
      "apiPageUrl": "http://test.com/data_3_apiPageUrl",
      "id": 103
    },
    {
      "apiMark": "data_4_apiMark",
      "apiMarkName": "data_4_apiMarkName",
      "apiDetailUrl": "http://test.com/data_4_apiDetailUrl",
      "apiUrl": "http://test.com/data_4_apiUrl",
      "apiPageUrl": "http://test.com/data_4_apiPageUrl",
      "id": 104
    },
    {
      "apiMark": "data_5_apiMark",
      "apiMarkName": "data_5_apiMarkName",
      "apiDetailUrl": "http://test.com/data_5_apiDetailUrl",
      "apiUrl": "http://test.com/data_5_apiUrl",
      "apiPageUrl": "http://test.com/data_5_apiPageUrl",
      "id": 105
    },
    {
      "apiMark": "data_6_apiMark",
      "apiMarkName": "data_6_apiMarkName",
      "apiDetailUrl": "http://test.com/data_6_apiDetailUrl",
      "apiUrl": "http://test.com/data_6_apiUrl",
      "apiPageUrl": "http://test.com/data_6_apiPageUrl",
      "id": 106
    },
    {
      "apiMark": "data_7_apiMark",
      "apiMarkName": "data_7_apiMarkName",
      "apiDetailUrl": "http://test.com/data_7_apiDetailUrl",
      "apiUrl": "http://test.com/data_7_apiUrl",
      "apiPageUrl": "http://test.com/data_7_apiPageUrl",
      "id": 107
    },
    {
      "apiMark": "data_8_apiMark",
      "apiMarkName": "data_8_apiMarkName",
      "apiDetailUrl": "http://test.com/data_8_apiDetailUrl",
      "apiUrl": "http://test.com/data_8_apiUrl",
      "apiPageUrl": "http://test.com/data_8_apiPageUrl",
      "id": 108
    },
    {
      "apiMark": "data_9_apiMark",
      "apiMarkName": "data_9_apiMarkName",
      "apiDetailUrl": "http://test.com/data_9_apiDetailUrl",
      "apiUrl": "http://test.com/data_9_apiUrl",
      "apiPageUrl": "http://test.com/data_9_apiPageUrl",
      "id": 109
    },
    {
      "apiMark": "data_10_apiMark",
      "apiMarkName": "data_10_apiMarkName",
      "apiDetailUrl": "http://test.com/data_10_apiDetailUrl",
      "apiUrl": "http://test.com/data_10_apiUrl",
      "apiPageUrl": "http://test.com/data_10_apiPageUrl",
      "id": 110
    },
    {
      "apiMark": "data_11_apiMark",
      "apiMarkName": "data_11_apiMarkName",
      "apiDetailUrl": "http://test.com/data_11_apiDetailUrl",
      "apiUrl": "http://test.com/data_11_apiUrl",
      "apiPageUrl": "http://test.com/data_11_apiPageUrl",
      "id": 111
    },
    {
      "apiMark": "data_12_apiMark",
      "apiMarkName": "data_12_apiMarkName",
      "apiDetailUrl": "http://test.com/data_12_apiDetailUrl",
      "apiUrl": "http://test.com/data_12_apiUrl",
      "apiPageUrl": "http://test.com/data_12_apiPageUrl",
      "id": 112
    },
    {
      "apiMark": "data_13_apiMark",
      "apiMarkName": "data_13_apiMarkName",
      "apiDetailUrl": "http://test.com/data_13_apiDetailUrl",
      "apiUrl": "http://test.com/data_13_apiUrl",
      "apiPageUrl": "http://test.com/data_13_apiPageUrl",
      "id": 113
    },
    {
      "apiMark": "data_14_apiMark",
      "apiMarkName": "data_14_apiMarkName",
      "apiDetailUrl": "http://test.com/data_14_apiDetailUrl",
      "apiUrl": "http://test.com/data_14_apiUrl",
      "apiPageUrl": "http://test.com/data_14_apiPageUrl",
      "id": 114
    }
  ],
  "errors": [
    {
      "field": "errors_0_field",
      "info": "errors_0_info"
    },
    {
      "field": "errors_1_field",
      "info": "errors_1_info"
    },
    {
      "field": "errors_2_field",
      "info": "errors_2_info"
    }
  ]
}